clds_pipeline/__init__.py
clds_pipeline/clds_pipeline.py
clds_pipeline/cli.py
clds_pipeline/coordinator.py
clds_pipeline/extractors.py
clds_pipeline/supported_lang.py
clds_pipeline/wordnet.py
clds_pipeline/nltk_data/corpora/wordnet.zip
clds_pipeline/nltk_data/corpora/wordnet_ic.zip
clds_pipeline-0.1.4.dist-info/DESCRIPTION.rst
clds_pipeline-0.1.4.dist-info/METADATA
clds_pipeline-0.1.4.dist-info/RECORD
clds_pipeline-0.1.4.dist-info/WHEEL
clds_pipeline-0.1.4.dist-info/entry_points.txt
clds_pipeline-0.1.4.dist-info/metadata.json
clds_pipeline-0.1.4.dist-info/top_level.txt
