Metadata-Version: 2.0
Name: clds-pipeline
Version: 0.1.4
Summary: Cross Language Document Similarity Pipeline for Master's Thesis
Home-page: https://github.com/gusennan/clds_pipeline
Author: Nate Guerin
Author-email: nathan.guerin@gmail.com
License: GNU General Public License v3
Keywords: clds_pipeline
Platform: UNKNOWN
Classifier: Development Status :: 2 - Pre-Alpha
Classifier: Intended Audience :: Developers
Classifier: License :: OSI Approved :: GNU General Public License v3 (GPLv3)
Classifier: Natural Language :: English
Classifier: Programming Language :: Python :: 2
Classifier: Programming Language :: Python :: 2.6
Classifier: Programming Language :: Python :: 2.7
Classifier: Programming Language :: Python :: 3
Classifier: Programming Language :: Python :: 3.3
Classifier: Programming Language :: Python :: 3.4
Classifier: Programming Language :: Python :: 3.5
Requires-Dist: Click (>=6.0)
Requires-Dist: nltk
Requires-Dist: numpy
